{
    "Индикативный курс": {
        "Доллар/Гривна": {
            "they_buy": "2621",
            "they_sell": "2629"
        },
        "Евро/Гривна": {
            "they_buy": "3115",
            "they_sell": "3150"
        },
        "Рубль/Гривна": {
            "they_buy": "0.445",
            "they_sell": "0.450"
        }
    },
    "Розница": {
        "Доллар/Гривна": {
            "they_buy": "2610",
            "they_sell": "2640"
        },
        "Евро/Гривна": {
            "they_buy": "3110",
            "they_sell": "3160"
        },
        "Рубль/Гривна": {
            "they_buy": "0.442",
            "they_sell": "0,453"
        }
    }
}