{
    "Индикативный курс": {
        "byn/uah": {
            "they_buy": "10.00",
            "they_sell": "12.00"
        },
        "eur/uah": {
            "they_buy": "27,40",
            "they_sell": "28,00"
        },
        "gbr/uah": {
            "they_buy": "30,00",
            "they_sell": "31,40"
        },
        "plh/uah": {
            "they_buy": "6,00",
            "they_sell": "6.30"
        },
        "rub/uah": {
            "they_buy": "0.382",
            "they_sell": "0.390"
        },
        "usd/uah": {
            "they_buy": "25,20",
            "they_sell": "25,60"
        }
    }
}