{
    "Индикативный курс": {
        "Доллар/Гривна": {
            "they_buy": "2603",
            "they_sell": "2613"
        },
        "Евро/Гривна": {
            "they_buy": "3200",
            "they_sell": "3225"
        },
        "Рубль/Гривна": {
            "they_buy": "0.416",
            "they_sell": "0.425"
        }
    },
    "Розница": {
        "Доллар/Гривна": {
            "they_buy": "2560",
            "they_sell": "2630"
        },
        "Евро/Гривна": {
            "they_buy": "3150",
            "they_sell": "3245"
        },
        "Рубль/Гривна": {
            "they_buy": "0.40",
            "they_sell": "0,435"
        }
    }
}