{
    "Индикативный курс": {
        "byn/uah": {
            "they_buy": "11.00",
            "they_sell": "12.50"
        },
        "eur/uah": {
            "they_buy": "26,50",
            "they_sell": "26,70"
        },
        "gbr/uah": {
            "they_buy": "29,4",
            "they_sell": "30,5"
        },
        "plh/uah": {
            "they_buy": "5,95",
            "they_sell": "6.15"
        },
        "rub/uah": {
            "they_buy": "0.374",
            "they_sell": "0.377"
        },
        "usd/uah": {
            "they_buy": "24,10",
            "they_sell": "24,22"
        }
    }
}