{
    "Индикативный курс": {
        "byn/uah": {
            "they_buy": "10.00",
            "they_sell": "14.00"
        },
        "eur/uah": {
            "they_buy": "26,60",
            "they_sell": "26,80"
        },
        "gbr/uah": {
            "they_buy": "30.30",
            "they_sell": "31.80"
        },
        "plh/uah": {
            "they_buy": "6,05",
            "they_sell": "6.30"
        },
        "rub/uah": {
            "they_buy": "0.373",
            "they_sell": "0.379"
        },
        "usd/uah": {
            "they_buy": "24,45",
            "they_sell": "24,60"
        }
    }
}